{
  "theme": "base",
  "themeVariables": {
    "primaryColor": "#E6F5F5",
    "primaryTextColor": "#1F2937",
    "primaryBorderColor": "#2B9E9E",
    "lineColor": "#6B7280",
    "secondaryColor": "#F3F4F6",
    "tertiaryColor": "#E8F0FE",
    "background": "#FFFFFF",
    "mainBkg": "#E6F5F5",
    "nodeBorder": "#2B9E9E",
    "clusterBkg": "#F9FAFB",
    "clusterBorder": "#D1D5DB",
    "titleColor": "#1F2937",
    "edgeLabelBackground": "#FFFFFF",
    "fontSize": "13px",
    "fontFamily": "Helvetica, Arial, sans-serif"
  }
}
